bot/__init__.py
bot/__main__.py
bot/helper/__init__.py
bot/helper/custom_filters.py
bot/helper/ext_utils/__init__.py
bot/helper/ext_utils/bot_utils.py
bot/helper/ext_utils/db_handler.py
bot/helper/ext_utils/exceptions.py
bot/helper/ext_utils/fs_utils.py
bot/helper/mirror_utils/__init__.py
bot/helper/mirror_utils/download_utils/__init__.py
bot/helper/mirror_utils/download_utils/aria2_download.py
bot/helper/mirror_utils/download_utils/direct_link_generator.py
bot/helper/mirror_utils/download_utils/download_helper.py
bot/helper/mirror_utils/download_utils/mega_downloader.py
bot/helper/mirror_utils/download_utils/telegram_downloader.py
bot/helper/mirror_utils/download_utils/youtube_dl_download_helper.py
bot/helper/mirror_utils/status_utils/__init__.py
bot/helper/mirror_utils/status_utils/aria_download_status.py
bot/helper/mirror_utils/status_utils/clone_status.py
bot/helper/mirror_utils/status_utils/extract_status.py
bot/helper/mirror_utils/status_utils/gdownload_status.py
bot/helper/mirror_utils/status_utils/listeners.py
bot/helper/mirror_utils/status_utils/mega_download_status.py
bot/helper/mirror_utils/status_utils/status.py
bot/helper/mirror_utils/status_utils/tar_status.py
bot/helper/mirror_utils/status_utils/telegram_download_status.py
bot/helper/mirror_utils/status_utils/upload_status.py
bot/helper/mirror_utils/status_utils/youtube_dl_download_status.py
bot/helper/mirror_utils/upload_utils/__init__.py
bot/helper/mirror_utils/upload_utils/gdriveTools.py
bot/helper/telegram_helper/__init__.py
bot/helper/telegram_helper/bot_commands.py
bot/helper/telegram_helper/button_build.py
bot/helper/telegram_helper/filters.py
bot/helper/telegram_helper/message_utils.py
bot/modules/__init__.py
bot/modules/authorize.py
bot/modules/cancel_mirror.py
bot/modules/clone.py
bot/modules/config.py
bot/modules/count.py
bot/modules/delete.py
bot/modules/eval.py
bot/modules/list.py
bot/modules/mirror.py
bot/modules/mirror_status.py
bot/modules/shell.py
bot/modules/speedtest.py
tgcd-1.1.0.dist-info/LICENSE
tgcd-1.1.0.dist-info/METADATA
tgcd-1.1.0.dist-info/WHEEL
tgcd-1.1.0.dist-info/entry_points.txt
tgcd-1.1.0.dist-info/top_level.txt
tgcd-1.1.0.dist-info/RECORD
